orange_cb_recsys/__init__.py
orange_cb_recsys/__main__.py
orange_cb_recsys/content_analyzer/__init__.py
orange_cb_recsys/content_analyzer/config.py
orange_cb_recsys/content_analyzer/content_analyzer_main.py
orange_cb_recsys/content_analyzer/lod_properties_retrieval.py
orange_cb_recsys/content_analyzer/raw_information_source.py
orange_cb_recsys/content_analyzer/content_representation/__init__.py
orange_cb_recsys/content_analyzer/content_representation/content.py
orange_cb_recsys/content_analyzer/content_representation/content_field.py
orange_cb_recsys/content_analyzer/embedding_learner/__init__.py
orange_cb_recsys/content_analyzer/embedding_learner/doc2vec.py
orange_cb_recsys/content_analyzer/embedding_learner/embedding_learner.py
orange_cb_recsys/content_analyzer/embedding_learner/fasttext.py
orange_cb_recsys/content_analyzer/embedding_learner/latent_semantic_analysis.py
orange_cb_recsys/content_analyzer/embedding_learner/random_indexing.py
orange_cb_recsys/content_analyzer/embedding_learner/word2vec.py
orange_cb_recsys/content_analyzer/field_content_production_techniques/__init__.py
orange_cb_recsys/content_analyzer/field_content_production_techniques/entity_linking.py
orange_cb_recsys/content_analyzer/field_content_production_techniques/field_content_production_technique.py
orange_cb_recsys/content_analyzer/field_content_production_techniques/synset_document_frequency.py
orange_cb_recsys/content_analyzer/field_content_production_techniques/tf_idf.py
orange_cb_recsys/content_analyzer/field_content_production_techniques/embedding_technique/__init__.py
orange_cb_recsys/content_analyzer/field_content_production_techniques/embedding_technique/combining_technique.py
orange_cb_recsys/content_analyzer/field_content_production_techniques/embedding_technique/embedding_source.py
orange_cb_recsys/content_analyzer/information_processor/__init__.py
orange_cb_recsys/content_analyzer/information_processor/information_processor.py
orange_cb_recsys-3.0.dist-info/LICENSE
orange_cb_recsys-3.0.dist-info/METADATA
orange_cb_recsys-3.0.dist-info/WHEEL
orange_cb_recsys-3.0.dist-info/top_level.txt
orange_cb_recsys-3.0.dist-info/RECORD
