Metadata-Version: 2.1
Name: orange-cb-recsys
Version: 3.0
Summary: Python Framework for Content-Based Recommeder Systems
Home-page: https://github.com/m3ttiw/orange_cb_recsys
Author: Roberto Barile, Francesco Benedetti, Carlo Parisi, Mattia Patruno
License: UNKNOWN
Platform: UNKNOWN
Requires-Python: >=3.8
Requires-Dist: pandas (==1.0.5)
Requires-Dist: PyYAML (==5.3.1)
Requires-Dist: numpy (==1.18.4)
Requires-Dist: gensim (==3.8.3)
Requires-Dist: nltk (==3.5)
Requires-Dist: babelpy (==1.0.1)
Requires-Dist: mysql (==0.0.2)
Requires-Dist: mysql-connector-python (==8.0.20)
Requires-Dist: wikipedia2vec (==1.0.4)
Requires-Dist: sklearn (==0.0)
Requires-Dist: SPARQLWrapper (==1.8.5)
Requires-Dist: textblob (==0.15.3)
Requires-Dist: matplotlib (==3.2.2)
Requires-Dist: pywsd (==1.2.4)
